cmaps/__init__.py
cmaps/_version.py
cmaps/cmaps.py
cmaps/colormap.py
cmaps/colormaps/ncar_ncl/3gauss.rgb
cmaps/colormaps/ncar_ncl/3saw.rgb
cmaps/colormaps/ncar_ncl/BkBlAqGrYeOrReViWh200.rgb
cmaps/colormaps/ncar_ncl/BlAqGrWh2YeOrReVi22.rgb
cmaps/colormaps/ncar_ncl/BlAqGrYeOrRe.rgb
cmaps/colormaps/ncar_ncl/BlAqGrYeOrReVi200.rgb
cmaps/colormaps/ncar_ncl/BlGrYeOrReVi200.rgb
cmaps/colormaps/ncar_ncl/BlRe.rgb
cmaps/colormaps/ncar_ncl/BlWhRe.rgb
cmaps/colormaps/ncar_ncl/BlueDarkOrange18.rgb
cmaps/colormaps/ncar_ncl/BlueDarkRed18.rgb
cmaps/colormaps/ncar_ncl/BlueGreen14.rgb
cmaps/colormaps/ncar_ncl/BlueRed.rgb
cmaps/colormaps/ncar_ncl/BlueRedGray.rgb
cmaps/colormaps/ncar_ncl/BlueWhiteOrangeRed.rgb
cmaps/colormaps/ncar_ncl/BlueYellowRed.rgb
cmaps/colormaps/ncar_ncl/BrownBlue12.rgb
cmaps/colormaps/ncar_ncl/CBR_coldhot.rgb
cmaps/colormaps/ncar_ncl/CBR_drywet.rgb
cmaps/colormaps/ncar_ncl/CBR_set3.rgb
cmaps/colormaps/ncar_ncl/CBR_wet.rgb
cmaps/colormaps/ncar_ncl/Cat12.rgb
cmaps/colormaps/ncar_ncl/Copyright
cmaps/colormaps/ncar_ncl/GHRSST_anomaly.rgb
cmaps/colormaps/ncar_ncl/GMT_cool.rgb
cmaps/colormaps/ncar_ncl/GMT_copper.rgb
cmaps/colormaps/ncar_ncl/GMT_drywet.rgb
cmaps/colormaps/ncar_ncl/GMT_gebco.rgb
cmaps/colormaps/ncar_ncl/GMT_globe.rgb
cmaps/colormaps/ncar_ncl/GMT_gray.rgb
cmaps/colormaps/ncar_ncl/GMT_haxby.rgb
cmaps/colormaps/ncar_ncl/GMT_hot.rgb
cmaps/colormaps/ncar_ncl/GMT_jet.rgb
cmaps/colormaps/ncar_ncl/GMT_nighttime.rgb
cmaps/colormaps/ncar_ncl/GMT_no_green.rgb
cmaps/colormaps/ncar_ncl/GMT_ocean.rgb
cmaps/colormaps/ncar_ncl/GMT_paired.rgb
cmaps/colormaps/ncar_ncl/GMT_panoply.rgb
cmaps/colormaps/ncar_ncl/GMT_polar.rgb
cmaps/colormaps/ncar_ncl/GMT_red2green.rgb
cmaps/colormaps/ncar_ncl/GMT_relief.rgb
cmaps/colormaps/ncar_ncl/GMT_relief_oceanonly.rgb
cmaps/colormaps/ncar_ncl/GMT_seis.rgb
cmaps/colormaps/ncar_ncl/GMT_split.rgb
cmaps/colormaps/ncar_ncl/GMT_topo.rgb
cmaps/colormaps/ncar_ncl/GMT_wysiwyg.rgb
cmaps/colormaps/ncar_ncl/GMT_wysiwygcont.rgb
cmaps-2.0.1.dist-info/LICENSE
cmaps-2.0.1.dist-info/METADATA
cmaps-2.0.1.dist-info/WHEEL
cmaps-2.0.1.dist-info/top_level.txt
cmaps-2.0.1.dist-info/RECORD
